rglogger.py
setup.cfg
setup.py
rglogger_fdh.egg-info/PKG-INFO
rglogger_fdh.egg-info/SOURCES.txt
rglogger_fdh.egg-info/dependency_links.txt
rglogger_fdh.egg-info/requires.txt
rglogger_fdh.egg-info/top_level.txt